xply/__init__.py
xply/connections.py
xply/pack.py
xply/utilities.py
xply-0.1.1.dist-info/LICENSE
xply-0.1.1.dist-info/METADATA
xply-0.1.1.dist-info/WHEEL
xply-0.1.1.dist-info/top_level.txt
xply-0.1.1.dist-info/RECORD
