Metadata-Version: 2.1
Name: xply
Version: 0.1.1
Summary: An exploit development framework for Python 3
Home-page: https://github.com/tobiasholl/xply
Author: Tobias Holl
Author-email: tobias.holl@tum.de
License: UNKNOWN
Platform: UNKNOWN
Classifier: Development Status :: 3 - Alpha
Classifier: Programming Language :: Python :: 3 :: Only
Classifier: Programming Language :: Python :: 3.7
Classifier: License :: OSI Approved :: MIT License
Classifier: Operating System :: OS Independent
Classifier: Topic :: Security
